modbus_remote/__init__.py
modbus_remote/modbus_deviceadapter.py
modbus_remote/modbus_models.py
modbus_remote/modbus_remote.py
modbus_remote-0.1.0.dist-info/LICENSE
modbus_remote-0.1.0.dist-info/METADATA
modbus_remote-0.1.0.dist-info/WHEEL
modbus_remote-0.1.0.dist-info/top_level.txt
modbus_remote-0.1.0.dist-info/RECORD
